int_set/__init__.py
int_set/int_set.py
int_set/math.py
int_set/step.py
int_set-0.1.1.dist-info/WHEEL
int_set-0.1.1.dist-info/METADATA
int_set-0.1.1.dist-info/RECORD
