Metadata-Version: 2.1
Name: int-set
Version: 0.1.1
Summary: 
Home-page: http://github.com/YutaUra/IntSet
License: Apache-2.0
Author: YutaUra
Author-email: yuuta3594@outlook.jp
Requires-Python: >=3.7,<4.0
Classifier: License :: OSI Approved :: Apache Software License
Classifier: Programming Language :: Python :: 3
Classifier: Programming Language :: Python :: 3.7
Classifier: Programming Language :: Python :: 3.8
Project-URL: Repository, http://github.com/YutaUra/IntSet
